setup.py
album_dl.egg-info/PKG-INFO
album_dl.egg-info/SOURCES.txt
album_dl.egg-info/dependency_links.txt
album_dl.egg-info/entry_points.txt
album_dl.egg-info/requires.txt
album_dl.egg-info/top_level.txt
albumdownloader/__init__.py
albumdownloader/__main__.py