Metadata-Version: 1.0
Name: album-dl
Version: 0.2.1
Summary: Python application to download full music albums using LastFM and Youtube
Home-page: http://ronan.gaillard.free.fr
Author: Ronan_Gaillard
Author-email: ronan.gaillard@supelec.fr
License: UNKNOWN
Platform: UNKNOWN
